[
  {
    "entries": [
      {
        "#gates": 162,
        "benchmark": "ex01",
        "depth": 17,
        "runtime": 7.341000080108643,
        "test": 98.421875,
        "train": 100.0,
        "valid": 98.09375
      },
      {
        "#gates": 142,
        "benchmark": "ex03",
        "depth": 16,
        "runtime": 15.262999534606934,
        "test": 97.71875,
        "train": 100.0,
        "valid": 97.28125
      },
      {
        "#gates": 135,
        "benchmark": "ex05",
        "depth": 17,
        "runtime": 29.54599952697754,
        "test": 97.359375,
        "train": 100.0,
        "valid": 97.28125
      },
      {
        "#gates": 745,
        "benchmark": "ex10",
        "depth": 22,
        "runtime": 35.7760009765625,
        "test": 86.78125,
        "train": 100.0,
        "valid": 87.703125
      },
      {
        "#gates": 516,
        "benchmark": "ex15",
        "depth": 22,
        "runtime": 29.21299934387207,
        "test": 91.109375,
        "train": 100.0,
        "valid": 91.625
      },
      {
        "#gates": 132,
        "benchmark": "ex07",
        "depth": 16,
        "runtime": 73.39299774169922,
        "test": 97.265625,
        "train": 100.0,
        "valid": 97.671875
      },
      {
        "#gates": 637,
        "benchmark": "ex11",
        "depth": 22,
        "runtime": 74.9520034790039,
        "test": 86.921875,
        "train": 100.0,
        "valid": 86.953125
      },
      {
        "#gates": 1768,
        "benchmark": "ex00",
        "depth": 25,
        "runtime": 84.33799743652344,
        "test": 66.375,
        "train": 100.0,
        "valid": 66.625
      },
      {
        "#gates": 439,
        "benchmark": "ex16",
        "depth": 20,
        "runtime": 55.10599899291992,
        "test": 90.921875,
        "train": 100.0,
        "valid": 90.359375
      },
      {
        "#gates": 615,
        "benchmark": "ex12",
        "depth": 21,
        "runtime": 159.24600219726563,
        "test": 84.96875,
        "train": 100.0,
        "valid": 83.796875
      },
      {
        "#gates": 3126,
        "benchmark": "ex20",
        "depth": 26,
        "runtime": 51.79899978637695,
        "test": 58.703125,
        "train": 100.0,
        "valid": 58.640625
      },
      {
        "#gates": 388,
        "benchmark": "ex17",
        "depth": 20,
        "runtime": 99.50900268554688,
        "test": 89.828125,
        "train": 100.0,
        "valid": 89.90625
      },
      {
        "#gates": 133,
        "benchmark": "ex09",
        "depth": 15,
        "runtime": 175.343994140625,
        "test": 96.953125,
        "train": 100.0,
        "valid": 97.453125
      },
      {
        "#gates": 488,
        "benchmark": "ex21",
        "depth": 26,
        "runtime": 11.654999732971191,
        "test": 96.03125,
        "train": 100.0,
        "valid": 95.515625
      },
      {
        "#gates": 1034,
        "benchmark": "ex23",
        "depth": 24,
        "runtime": 64.38600158691406,
        "test": 82.390625,
        "train": 100.0,
        "valid": 81.140625
      },
      {
        "#gates": 1951,
        "benchmark": "ex02",
        "depth": 22,
        "runtime": 242.97500610351563,
        "test": 51.140625,
        "train": 100.0,
        "valid": 50.9375
      },
      {
        "#gates": 364,
        "benchmark": "ex18",
        "depth": 19,
        "runtime": 209.0590057373047,
        "test": 89.34375,
        "train": 100.0,
        "valid": 88.953125
      },
      {
        "#gates": 2428,
        "benchmark": "ex22",
        "depth": 23,
        "runtime": 138.6959991455078,
        "test": 49.421875,
        "train": 100.0,
        "valid": 50.796875
      },
      {
        "#gates": 588,
        "benchmark": "ex13",
        "depth": 20,
        "runtime": 354.927001953125,
        "test": 82.71875,
        "train": 100.0,
        "valid": 82.125
      },
      {
        "#gates": 151,
        "benchmark": "ex30",
        "depth": 18,
        "runtime": 5.60699987411499,
        "test": 98.359375,
        "train": 100.0,
        "valid": 98.515625
      },
      {
        "#gates": 158,
        "benchmark": "ex31",
        "depth": 17,
        "runtime": 11.807999610900879,
        "test": 98.09375,
        "train": 100.0,
        "valid": 98.0625
      },
      {
        "#gates": 156,
        "benchmark": "ex32",
        "depth": 17,
        "runtime": 20.1299991607666,
        "test": 97.953125,
        "train": 100.0,
        "valid": 97.96875
      },
      {
        "#gates": 1769,
        "benchmark": "ex25",
        "depth": 22,
        "runtime": 240.65899658203125,
        "test": 58.203125,
        "train": 100.0,
        "valid": 57.0
      },
      {
        "#gates": 146,
        "benchmark": "ex33",
        "depth": 16,
        "runtime": 26.649999618530273,
        "test": 97.6875,
        "train": 100.0,
        "valid": 98.015625
      },
      {
        "#gates": 1994,
        "benchmark": "ex24",
        "depth": 22,
        "runtime": 263.33099365234375,
        "test": 49.875,
        "train": 100.0,
        "valid": 48.890625
      },
      {
        "#gates": 146,
        "benchmark": "ex34",
        "depth": 16,
        "runtime": 35.33700180053711,
        "test": 97.484375,
        "train": 100.0,
        "valid": 97.25
      },
      {
        "#gates": 1694,
        "benchmark": "ex04",
        "depth": 21,
        "runtime": 479.427001953125,
        "test": 49.96875,
        "train": 100.0,
        "valid": 49.640625
      },
      {
        "#gates": 140,
        "benchmark": "ex35",
        "depth": 16,
        "runtime": 40.27199935913086,
        "test": 97.359375,
        "train": 100.0,
        "valid": 97.609375
      },
      {
        "#gates": 342,
        "benchmark": "ex19",
        "depth": 19,
        "runtime": 396.8169860839844,
        "test": 87.875,
        "train": 100.0,
        "valid": 88.765625
      },
      {
        "#gates": 140,
        "benchmark": "ex36",
        "depth": 16,
        "runtime": 43.00600051879883,
        "test": 97.234375,
        "train": 100.0,
        "valid": 97.46875
      },
      {
        "#gates": 147,
        "benchmark": "ex41",
        "depth": 17,
        "runtime": 4.017000198364258,
        "test": 100.0,
        "train": 100.0,
        "valid": 100.0
      },
      {
        "#gates": 1403,
        "benchmark": "ex40",
        "depth": 25,
        "runtime": 25.180999755859375,
        "test": 86.03125,
        "train": 100.0,
        "valid": 86.125
      },
      {
        "#gates": 152,
        "benchmark": "ex37",
        "depth": 16,
        "runtime": 60.42599868774414,
        "test": 97.265625,
        "train": 100.0,
        "valid": 97.3125
      },
      {
        "#gates": 443,
        "benchmark": "ex14",
        "depth": 19,
        "runtime": 509.2300109863281,
        "test": 85.078125,
        "train": 100.0,
        "valid": 85.828125
      },
      {
        "#gates": 139,
        "benchmark": "ex38",
        "depth": 16,
        "runtime": 60.698001861572266,
        "test": 97.390625,
        "train": 100.0,
        "valid": 97.734375
      },
      {
        "#gates": 140,
        "benchmark": "ex39",
        "depth": 17,
        "runtime": 61.099998474121094,
        "test": 97.296875,
        "train": 100.0,
        "valid": 97.46875
      },
      {
        "#gates": 1747,
        "benchmark": "ex43",
        "depth": 25,
        "runtime": 36.08599853515625,
        "test": 79.53125,
        "train": 100.0,
        "valid": 79.9375
      },
      {
        "#gates": 2476,
        "benchmark": "ex42",
        "depth": 25,
        "runtime": 123.44200134277344,
        "test": 50.375,
        "train": 100.0,
        "valid": 51.328125
      },
      {
        "#gates": 1572,
        "benchmark": "ex27",
        "depth": 21,
        "runtime": 424.05999755859375,
        "test": 52.59375,
        "train": 100.0,
        "valid": 53.359375
      },
      {
        "#gates": 2454,
        "benchmark": "ex45",
        "depth": 23,
        "runtime": 137.83200073242188,
        "test": 49.90625,
        "train": 100.0,
        "valid": 49.671875
      },
      {
        "#gates": 388,
        "benchmark": "ex50",
        "depth": 23,
        "runtime": 11.890000343322754,
        "test": 94.859375,
        "train": 100.0,
        "valid": 94.9375
      },
      {
        "#gates": 1703,
        "benchmark": "ex26",
        "depth": 22,
        "runtime": 463.4469909667969,
        "test": 50.34375,
        "train": 100.0,
        "valid": 50.21875
      },
      {
        "#gates": 1990,
        "benchmark": "ex44",
        "depth": 22,
        "runtime": 248.0019989013672,
        "test": 49.0,
        "train": 100.0,
        "valid": 50.140625
      },
      {
        "#gates": 866,
        "benchmark": "ex53",
        "depth": 21,
        "runtime": 74.15899658203125,
        "test": 82.03125,
        "train": 100.0,
        "valid": 81.140625
      },
      {
        "#gates": 1452,
        "benchmark": "ex06",
        "depth": 21,
        "runtime": 788.447998046875,
        "test": 50.484375,
        "train": 100.0,
        "valid": 49.671875
      },
      {
        "#gates": 171,
        "benchmark": "ex55",
        "depth": 20,
        "runtime": 15.375,
        "test": 96.953125,
        "train": 100.0,
        "valid": 97.1875
      },
      {
        "#gates": 299,
        "benchmark": "ex54",
        "depth": 20,
        "runtime": 32.12799835205078,
        "test": 94.15625,
        "train": 100.0,
        "valid": 93.859375
      },
      {
        "#gates": 124,
        "benchmark": "ex57",
        "depth": 18,
        "runtime": 7.0320000648498535,
        "test": 98.265625,
        "train": 100.0,
        "valid": 98.125
      },
      {
        "#gates": 1531,
        "benchmark": "ex51",
        "depth": 22,
        "runtime": 131.57699584960938,
        "test": 70.0625,
        "train": 100.0,
        "valid": 69.90625
      },
      {
        "#gates": 2002,
        "benchmark": "ex47",
        "depth": 23,
        "runtime": 276.2659912109375,
        "test": 50.0,
        "train": 100.0,
        "valid": 49.609375
      },
      {
        "#gates": 150,
        "benchmark": "ex56",
        "depth": 19,
        "runtime": 32.744998931884766,
        "test": 96.203125,
        "train": 100.0,
        "valid": 96.171875
      },
      {
        "#gates": 44,
        "benchmark": "ex61",
        "depth": 14,
        "runtime": 4.135000228881836,
        "test": 99.65625,
        "train": 100.0,
        "valid": 99.671875
      },
      {
        "#gates": 98,
        "benchmark": "ex63",
        "depth": 17,
        "runtime": 6.599999904632568,
        "test": 99.203125,
        "train": 100.0,
        "valid": 99.09375
      },
      {
        "#gates": 209,
        "benchmark": "ex58",
        "depth": 19,
        "runtime": 33.22800064086914,
        "test": 94.6875,
        "train": 100.0,
        "valid": 95.4375
      },
      {
        "#gates": 7,
        "benchmark": "ex64",
        "depth": 7,
        "runtime": 2.8420000076293945,
        "test": 100.0,
        "train": 100.0,
        "valid": 100.0
      },
      {
        "#gates": 101,
        "benchmark": "ex65",
        "depth": 18,
        "runtime": 4.613999843597412,
        "test": 99.546875,
        "train": 100.0,
        "valid": 99.3125
      },
      {
        "#gates": 423,
        "benchmark": "ex60",
        "depth": 21,
        "runtime": 33.81800079345703,
        "test": 93.71875,
        "train": 100.0,
        "valid": 93.484375
      },
      {
        "#gates": 318,
        "benchmark": "ex62",
        "depth": 21,
        "runtime": 29.538000106811523,
        "test": 95.125,
        "train": 100.0,
        "valid": 94.578125
      },
      {
        "#gates": 129,
        "benchmark": "ex69",
        "depth": 19,
        "runtime": 4.941999912261963,
        "test": 98.765625,
        "train": 100.0,
        "valid": 98.78125
      },
      {
        "#gates": 179,
        "benchmark": "ex68",
        "depth": 21,
        "runtime": 12.204999923706055,
        "test": 97.171875,
        "train": 100.0,
        "valid": 97.296875
      },
      {
        "#gates": 1441,
        "benchmark": "ex52",
        "depth": 23,
        "runtime": 181.5679931640625,
        "test": 66.71875,
        "train": 100.0,
        "valid": 67.796875
      },
      {
        "#gates": 160,
        "benchmark": "ex70",
        "depth": 19,
        "runtime": 6.50600004196167,
        "test": 98.21875,
        "train": 100.0,
        "valid": 98.375
      },
      {
        "#gates": 142,
        "benchmark": "ex71",
        "depth": 21,
        "runtime": 5.168000221252441,
        "test": 99.0,
        "train": 100.0,
        "valid": 98.921875
      },
      {
        "#gates": 15,
        "benchmark": "ex74",
        "depth": 15,
        "runtime": 3.8889999389648438,
        "test": 100.0,
        "train": 100.0,
        "valid": 100.0
      },
      {
        "#gates": 440,
        "benchmark": "ex66",
        "depth": 20,
        "runtime": 39.88199996948242,
        "test": 92.171875,
        "train": 100.0,
        "valid": 92.171875
      },
      {
        "#gates": 417,
        "benchmark": "ex67",
        "depth": 20,
        "runtime": 36.26100158691406,
        "test": 93.015625,
        "train": 100.0,
        "valid": 93.328125
      },
      {
        "#gates": 225,
        "benchmark": "ex72",
        "depth": 21,
        "runtime": 16.448999404907227,
        "test": 97.0,
        "train": 100.0,
        "valid": 95.953125
      },
      {
        "#gates": 825,
        "benchmark": "ex73",
        "depth": 25,
        "runtime": 17.93600082397461,
        "test": 93.21875,
        "train": 100.0,
        "valid": 93.0
      },
      {
        "#gates": 1508,
        "benchmark": "ex75",
        "depth": 23,
        "runtime": 32.97700119018555,
        "test": 80.03125,
        "train": 100.0,
        "valid": 80.921875
      },
      {
        "#gates": 1565,
        "benchmark": "ex76",
        "depth": 24,
        "runtime": 30.19300079345703,
        "test": 80.46875,
        "train": 100.0,
        "valid": 80.890625
      },
      {
        "#gates": 1569,
        "benchmark": "ex77",
        "depth": 24,
        "runtime": 38.62900161743164,
        "test": 80.34375,
        "train": 100.0,
        "valid": 80.515625
      },
      {
        "#gates": 1569,
        "benchmark": "ex79",
        "depth": 24,
        "runtime": 38.99100112915039,
        "test": 80.34375,
        "train": 100.0,
        "valid": 80.515625
      },
      {
        "#gates": 3215,
        "benchmark": "ex78",
        "depth": 26,
        "runtime": 54.0629997253418,
        "test": 56.421875,
        "train": 100.0,
        "valid": 57.15625
      },
      {
        "#gates": 1673,
        "benchmark": "ex46",
        "depth": 22,
        "runtime": 459.0010070800781,
        "test": 50.515625,
        "train": 100.0,
        "valid": 49.453125
      },
      {
        "#gates": 217,
        "benchmark": "ex59",
        "depth": 17,
        "runtime": 219.7530059814453,
        "test": 94.671875,
        "train": 100.0,
        "valid": 94.421875
      },
      {
        "#gates": 360,
        "benchmark": "ex82",
        "depth": 23,
        "runtime": 124.56800079345703,
        "test": 93.4375,
        "train": 100.0,
        "valid": 92.75
      },
      {
        "#gates": 519,
        "benchmark": "ex81",
        "depth": 27,
        "runtime": 136.2830047607422,
        "test": 88.34375,
        "train": 100.0,
        "valid": 89.4375
      },
      {
        "#gates": 290,
        "benchmark": "ex83",
        "depth": 21,
        "runtime": 122.77899932861328,
        "test": 95.703125,
        "train": 100.0,
        "valid": 95.734375
      },
      {
        "#gates": 401,
        "benchmark": "ex84",
        "depth": 25,
        "runtime": 117.97000122070313,
        "test": 92.859375,
        "train": 100.0,
        "valid": 92.84375
      },
      {
        "#gates": 689,
        "benchmark": "ex80",
        "depth": 32,
        "runtime": 164.2169952392578,
        "test": 86.15625,
        "train": 100.0,
        "valid": 86.765625
      },
      {
        "#gates": 352,
        "benchmark": "ex85",
        "depth": 31,
        "runtime": 110.23999786376953,
        "test": 94.265625,
        "train": 100.0,
        "valid": 93.921875
      },
      {
        "#gates": 1681,
        "benchmark": "ex49",
        "depth": 22,
        "runtime": 501.9429931640625,
        "test": 50.234375,
        "train": 100.0,
        "valid": 49.5625
      },
      {
        "#gates": 300,
        "benchmark": "ex86",
        "depth": 23,
        "runtime": 111.41600036621094,
        "test": 95.28125,
        "train": 100.0,
        "valid": 95.4375
      },
      {
        "#gates": 337,
        "benchmark": "ex87",
        "depth": 23,
        "runtime": 110.53800201416016,
        "test": 94.4375,
        "train": 100.0,
        "valid": 94.78125
      },
      {
        "#gates": 410,
        "benchmark": "ex88",
        "depth": 28,
        "runtime": 112.70099639892578,
        "test": 93.453125,
        "train": 100.0,
        "valid": 93.703125
      },
      {
        "#gates": 377,
        "benchmark": "ex89",
        "depth": 20,
        "runtime": 114.93499755859375,
        "test": 93.5,
        "train": 100.0,
        "valid": 93.875
      },
      {
        "#gates": 1483,
        "benchmark": "ex28",
        "depth": 21,
        "runtime": 915.0330200195313,
        "test": 50.078125,
        "train": 100.0,
        "valid": 50.921875
      },
      {
        "#gates": 1487,
        "benchmark": "ex29",
        "depth": 21,
        "runtime": 896.2130126953125,
        "test": 52.421875,
        "train": 100.0,
        "valid": 50.875
      },
      {
        "#gates": 1445,
        "benchmark": "ex48",
        "depth": 21,
        "runtime": 869.2769775390625,
        "test": 50.390625,
        "train": 100.0,
        "valid": 49.546875
      },
      {
        "#gates": 1313,
        "benchmark": "ex08",
        "depth": 20,
        "runtime": 1626.18505859375,
        "test": 49.40625,
        "train": 100.0,
        "valid": 49.921875
      },
      {
        "#gates": 802,
        "benchmark": "ex95",
        "depth": 48,
        "runtime": 832.6840209960938,
        "test": 73.734375,
        "train": 100.0,
        "valid": 74.5
      },
      {
        "#gates": 1140,
        "benchmark": "ex92",
        "depth": 95,
        "runtime": 927.77099609375,
        "test": 61.65625,
        "train": 99.890625,
        "valid": 63.09375
      },
      {
        "#gates": 965,
        "benchmark": "ex93",
        "depth": 49,
        "runtime": 982.8889770507813,
        "test": 69.640625,
        "train": 99.921875,
        "valid": 69.03125
      },
      {
        "#gates": 1118,
        "benchmark": "ex98",
        "depth": 46,
        "runtime": 926.8079833984375,
        "test": 61.03125,
        "train": 100.0,
        "valid": 63.5
      },
      {
        "#gates": 1209,
        "benchmark": "ex91",
        "depth": 55,
        "runtime": 1076.615966796875,
        "test": 59.25,
        "train": 100.0,
        "valid": 59.28125
      },
      {
        "#gates": 1184,
        "benchmark": "ex97",
        "depth": 61,
        "runtime": 987.4290161132813,
        "test": 61.125,
        "train": 99.953125,
        "valid": 61.5
      },
      {
        "#gates": 1248,
        "benchmark": "ex94",
        "depth": 73,
        "runtime": 1017.7890014648438,
        "test": 56.96875,
        "train": 99.921875,
        "valid": 57.0625
      },
      {
        "#gates": 1107,
        "benchmark": "ex99",
        "depth": 45,
        "runtime": 962.7420043945313,
        "test": 63.03125,
        "train": 100.0,
        "valid": 64.046875
      },
      {
        "#gates": 1304,
        "benchmark": "ex90",
        "depth": 63,
        "runtime": 1144.364013671875,
        "test": 53.9375,
        "train": 99.96875,
        "valid": 54.703125
      },
      {
        "#gates": 1111,
        "benchmark": "ex96",
        "depth": 45,
        "runtime": 1060.1510009765625,
        "test": 62.953125,
        "train": 99.984375,
        "valid": 62.515625
      }
    ],
    "version": "07f1b3b2"
  }
]
