[
  {
    "entries": [
      {
        "#gates": 165,
        "benchmark": "ex01",
        "depth": 18,
        "runtime": 3.3559999465942383,
        "test": 98.359375,
        "train": 100.0,
        "valid": 98.09375
      },
      {
        "#gates": 142,
        "benchmark": "ex03",
        "depth": 16,
        "runtime": 4.252999782562256,
        "test": 97.71875,
        "train": 100.0,
        "valid": 97.28125
      },
      {
        "#gates": 136,
        "benchmark": "ex05",
        "depth": 17,
        "runtime": 5.473999977111816,
        "test": 97.484375,
        "train": 100.0,
        "valid": 97.359375
      },
      {
        "#gates": 134,
        "benchmark": "ex07",
        "depth": 16,
        "runtime": 7.116000175476074,
        "test": 97.4375,
        "train": 100.0,
        "valid": 97.703125
      },
      {
        "#gates": 135,
        "benchmark": "ex09",
        "depth": 15,
        "runtime": 11.550999641418457,
        "test": 97.484375,
        "train": 100.0,
        "valid": 97.71875
      },
      {
        "#gates": 634,
        "benchmark": "ex11",
        "depth": 22,
        "runtime": 8.597999572753906,
        "test": 87.140625,
        "train": 100.0,
        "valid": 86.71875
      },
      {
        "#gates": 766,
        "benchmark": "ex10",
        "depth": 22,
        "runtime": 5.158999919891357,
        "test": 87.046875,
        "train": 100.0,
        "valid": 87.765625
      },
      {
        "#gates": 613,
        "benchmark": "ex12",
        "depth": 21,
        "runtime": 10.869999885559082,
        "test": 85.0,
        "train": 100.0,
        "valid": 83.796875
      },
      {
        "#gates": 1781,
        "benchmark": "ex00",
        "depth": 24,
        "runtime": 9.677000045776367,
        "test": 66.3125,
        "train": 100.0,
        "valid": 67.25
      },
      {
        "#gates": 571,
        "benchmark": "ex13",
        "depth": 21,
        "runtime": 16.875,
        "test": 82.546875,
        "train": 100.0,
        "valid": 82.09375
      },
      {
        "#gates": 1713,
        "benchmark": "ex04",
        "depth": 21,
        "runtime": 23.711999893188477,
        "test": 49.984375,
        "train": 100.0,
        "valid": 50.3125
      },
      {
        "#gates": 1959,
        "benchmark": "ex02",
        "depth": 24,
        "runtime": 15.340999603271484,
        "test": 51.0625,
        "train": 100.0,
        "valid": 51.03125
      },
      {
        "#gates": 517,
        "benchmark": "ex15",
        "depth": 22,
        "runtime": 4.544000148773193,
        "test": 90.9375,
        "train": 100.0,
        "valid": 91.6875
      },
      {
        "#gates": 449,
        "benchmark": "ex14",
        "depth": 19,
        "runtime": 24.457000732421875,
        "test": 85.328125,
        "train": 100.0,
        "valid": 85.953125
      },
      {
        "#gates": 1474,
        "benchmark": "ex06",
        "depth": 21,
        "runtime": 38.33399963378906,
        "test": 50.234375,
        "train": 100.0,
        "valid": 50.203125
      },
      {
        "#gates": 443,
        "benchmark": "ex16",
        "depth": 21,
        "runtime": 5.811999797821045,
        "test": 90.890625,
        "train": 100.0,
        "valid": 90.5625
      },
      {
        "#gates": 393,
        "benchmark": "ex17",
        "depth": 20,
        "runtime": 7.5,
        "test": 90.65625,
        "train": 100.0,
        "valid": 90.40625
      },
      {
        "#gates": 473,
        "benchmark": "ex21",
        "depth": 26,
        "runtime": 4.636000156402588,
        "test": 96.3125,
        "train": 100.0,
        "valid": 95.765625
      },
      {
        "#gates": 368,
        "benchmark": "ex18",
        "depth": 19,
        "runtime": 12.36400032043457,
        "test": 89.5625,
        "train": 100.0,
        "valid": 89.421875
      },
      {
        "#gates": 344,
        "benchmark": "ex19",
        "depth": 20,
        "runtime": 19.367000579833984,
        "test": 88.4375,
        "train": 100.0,
        "valid": 88.578125
      },
      {
        "#gates": 1331,
        "benchmark": "ex08",
        "depth": 21,
        "runtime": 62.70100021362305,
        "test": 49.5625,
        "train": 100.0,
        "valid": 49.34375
      },
      {
        "#gates": 1032,
        "benchmark": "ex23",
        "depth": 24,
        "runtime": 7.181000232696533,
        "test": 82.3125,
        "train": 100.0,
        "valid": 80.84375
      },
      {
        "#gates": 1770,
        "benchmark": "ex25",
        "depth": 22,
        "runtime": 14.791000366210938,
        "test": 57.515625,
        "train": 100.0,
        "valid": 57.03125
      },
      {
        "#gates": 2454,
        "benchmark": "ex22",
        "depth": 24,
        "runtime": 14.909000396728516,
        "test": 49.390625,
        "train": 100.0,
        "valid": 50.765625
      },
      {
        "#gates": 2006,
        "benchmark": "ex24",
        "depth": 23,
        "runtime": 16.759000778198242,
        "test": 49.75,
        "train": 100.0,
        "valid": 49.09375
      },
      {
        "#gates": 1724,
        "benchmark": "ex26",
        "depth": 22,
        "runtime": 22.884000778198242,
        "test": 50.359375,
        "train": 100.0,
        "valid": 50.65625
      },
      {
        "#gates": 1587,
        "benchmark": "ex27",
        "depth": 21,
        "runtime": 20.792999267578125,
        "test": 52.515625,
        "train": 100.0,
        "valid": 53.671875
      },
      {
        "#gates": 151,
        "benchmark": "ex30",
        "depth": 18,
        "runtime": 3.1070001125335693,
        "test": 98.359375,
        "train": 100.0,
        "valid": 98.515625
      },
      {
        "#gates": 157,
        "benchmark": "ex31",
        "depth": 17,
        "runtime": 3.4670000076293945,
        "test": 98.109375,
        "train": 100.0,
        "valid": 98.109375
      },
      {
        "#gates": 156,
        "benchmark": "ex32",
        "depth": 17,
        "runtime": 3.8570001125335693,
        "test": 97.953125,
        "train": 100.0,
        "valid": 97.96875
      },
      {
        "#gates": 146,
        "benchmark": "ex33",
        "depth": 16,
        "runtime": 4.908999919891357,
        "test": 97.6875,
        "train": 100.0,
        "valid": 98.015625
      },
      {
        "#gates": 144,
        "benchmark": "ex35",
        "depth": 16,
        "runtime": 5.201000213623047,
        "test": 97.359375,
        "train": 100.0,
        "valid": 97.703125
      },
      {
        "#gates": 1515,
        "benchmark": "ex28",
        "depth": 21,
        "runtime": 34.42100143432617,
        "test": 49.625,
        "train": 100.0,
        "valid": 50.921875
      },
      {
        "#gates": 149,
        "benchmark": "ex34",
        "depth": 16,
        "runtime": 5.2230000495910645,
        "test": 97.5,
        "train": 100.0,
        "valid": 97.390625
      },
      {
        "#gates": 140,
        "benchmark": "ex36",
        "depth": 17,
        "runtime": 5.394999980926514,
        "test": 97.328125,
        "train": 100.0,
        "valid": 97.578125
      },
      {
        "#gates": 3213,
        "benchmark": "ex20",
        "depth": 28,
        "runtime": 14.663999557495117,
        "test": 58.78125,
        "train": 100.0,
        "valid": 58.28125
      },
      {
        "#gates": 152,
        "benchmark": "ex37",
        "depth": 16,
        "runtime": 6.103000164031982,
        "test": 97.3125,
        "train": 100.0,
        "valid": 97.390625
      },
      {
        "#gates": 147,
        "benchmark": "ex41",
        "depth": 17,
        "runtime": 3.319999933242798,
        "test": 100.0,
        "train": 100.0,
        "valid": 100.0
      },
      {
        "#gates": 143,
        "benchmark": "ex38",
        "depth": 16,
        "runtime": 6.683000087738037,
        "test": 97.625,
        "train": 100.0,
        "valid": 97.90625
      },
      {
        "#gates": 138,
        "benchmark": "ex39",
        "depth": 17,
        "runtime": 6.122000217437744,
        "test": 97.46875,
        "train": 100.0,
        "valid": 97.453125
      },
      {
        "#gates": 1500,
        "benchmark": "ex29",
        "depth": 22,
        "runtime": 34.143001556396484,
        "test": 52.390625,
        "train": 100.0,
        "valid": 50.625
      },
      {
        "#gates": 1435,
        "benchmark": "ex40",
        "depth": 26,
        "runtime": 6.866000175476074,
        "test": 85.671875,
        "train": 100.0,
        "valid": 85.84375
      },
      {
        "#gates": 1807,
        "benchmark": "ex43",
        "depth": 27,
        "runtime": 7.578999996185303,
        "test": 79.375,
        "train": 100.0,
        "valid": 79.796875
      },
      {
        "#gates": 394,
        "benchmark": "ex50",
        "depth": 24,
        "runtime": 3.562999963760376,
        "test": 94.828125,
        "train": 100.0,
        "valid": 94.953125
      },
      {
        "#gates": 2007,
        "benchmark": "ex44",
        "depth": 23,
        "runtime": 16.134000778198242,
        "test": 48.453125,
        "train": 100.0,
        "valid": 50.875
      },
      {
        "#gates": 1699,
        "benchmark": "ex46",
        "depth": 22,
        "runtime": 23.891000747680664,
        "test": 50.703125,
        "train": 100.0,
        "valid": 49.265625
      },
      {
        "#gates": 2018,
        "benchmark": "ex47",
        "depth": 24,
        "runtime": 17.702999114990234,
        "test": 50.296875,
        "train": 100.0,
        "valid": 49.703125
      },
      {
        "#gates": 1453,
        "benchmark": "ex48",
        "depth": 21,
        "runtime": 35.42599868774414,
        "test": 50.625,
        "train": 100.0,
        "valid": 49.484375
      },
      {
        "#gates": 2443,
        "benchmark": "ex42",
        "depth": 25,
        "runtime": 13.847000122070313,
        "test": 50.125,
        "train": 100.0,
        "valid": 51.0
      },
      {
        "#gates": 2476,
        "benchmark": "ex45",
        "depth": 24,
        "runtime": 13.454999923706055,
        "test": 49.5625,
        "train": 100.0,
        "valid": 49.9375
      },
      {
        "#gates": 172,
        "benchmark": "ex55",
        "depth": 21,
        "runtime": 4.03000020980835,
        "test": 97.0625,
        "train": 100.0,
        "valid": 97.25
      },
      {
        "#gates": 154,
        "benchmark": "ex56",
        "depth": 19,
        "runtime": 4.382999897003174,
        "test": 96.234375,
        "train": 100.0,
        "valid": 96.28125
      },
      {
        "#gates": 299,
        "benchmark": "ex54",
        "depth": 20,
        "runtime": 4.5929999351501465,
        "test": 94.078125,
        "train": 100.0,
        "valid": 93.734375
      },
      {
        "#gates": 126,
        "benchmark": "ex57",
        "depth": 18,
        "runtime": 3.565999984741211,
        "test": 98.28125,
        "train": 100.0,
        "valid": 98.09375
      },
      {
        "#gates": 44,
        "benchmark": "ex61",
        "depth": 14,
        "runtime": 2.984999895095825,
        "test": 99.65625,
        "train": 100.0,
        "valid": 99.671875
      },
      {
        "#gates": 216,
        "benchmark": "ex58",
        "depth": 19,
        "runtime": 4.578000068664551,
        "test": 94.921875,
        "train": 100.0,
        "valid": 95.6875
      },
      {
        "#gates": 98,
        "benchmark": "ex63",
        "depth": 17,
        "runtime": 4.084000110626221,
        "test": 99.203125,
        "train": 100.0,
        "valid": 99.09375
      },
      {
        "#gates": 878,
        "benchmark": "ex53",
        "depth": 21,
        "runtime": 6.953000068664551,
        "test": 81.90625,
        "train": 100.0,
        "valid": 81.09375
      },
      {
        "#gates": 429,
        "benchmark": "ex60",
        "depth": 21,
        "runtime": 4.908999919891357,
        "test": 93.640625,
        "train": 100.0,
        "valid": 93.578125
      },
      {
        "#gates": 229,
        "benchmark": "ex59",
        "depth": 18,
        "runtime": 11.65999984741211,
        "test": 94.265625,
        "train": 100.0,
        "valid": 94.3125
      },
      {
        "#gates": 7,
        "benchmark": "ex64",
        "depth": 7,
        "runtime": 3.184000015258789,
        "test": 100.0,
        "train": 100.0,
        "valid": 100.0
      },
      {
        "#gates": 1683,
        "benchmark": "ex49",
        "depth": 23,
        "runtime": 21.777000427246094,
        "test": 50.125,
        "train": 100.0,
        "valid": 49.84375
      },
      {
        "#gates": 322,
        "benchmark": "ex62",
        "depth": 21,
        "runtime": 5.260000228881836,
        "test": 95.0625,
        "train": 100.0,
        "valid": 94.515625
      },
      {
        "#gates": 101,
        "benchmark": "ex65",
        "depth": 18,
        "runtime": 3.5820000171661377,
        "test": 99.546875,
        "train": 100.0,
        "valid": 99.3125
      },
      {
        "#gates": 111,
        "benchmark": "ex69",
        "depth": 19,
        "runtime": 3.1040000915527344,
        "test": 99.03125,
        "train": 100.0,
        "valid": 99.046875
      },
      {
        "#gates": 160,
        "benchmark": "ex70",
        "depth": 19,
        "runtime": 3.614000082015991,
        "test": 98.234375,
        "train": 100.0,
        "valid": 98.375
      },
      {
        "#gates": 178,
        "benchmark": "ex68",
        "depth": 21,
        "runtime": 3.9639999866485596,
        "test": 97.171875,
        "train": 100.0,
        "valid": 97.328125
      },
      {
        "#gates": 141,
        "benchmark": "ex71",
        "depth": 21,
        "runtime": 3.328000068664551,
        "test": 98.96875,
        "train": 100.0,
        "valid": 98.828125
      },
      {
        "#gates": 45,
        "benchmark": "ex74",
        "depth": 30,
        "runtime": 4.23199987411499,
        "test": 100.0,
        "train": 100.0,
        "valid": 100.0
      },
      {
        "#gates": 223,
        "benchmark": "ex72",
        "depth": 21,
        "runtime": 4.330999851226807,
        "test": 97.015625,
        "train": 100.0,
        "valid": 95.921875
      },
      {
        "#gates": 1525,
        "benchmark": "ex51",
        "depth": 23,
        "runtime": 10.545999526977539,
        "test": 70.296875,
        "train": 100.0,
        "valid": 70.25
      },
      {
        "#gates": 1463,
        "benchmark": "ex52",
        "depth": 23,
        "runtime": 11.559000015258789,
        "test": 66.953125,
        "train": 100.0,
        "valid": 68.15625
      },
      {
        "#gates": 434,
        "benchmark": "ex66",
        "depth": 21,
        "runtime": 5.811999797821045,
        "test": 92.015625,
        "train": 100.0,
        "valid": 92.3125
      },
      {
        "#gates": 426,
        "benchmark": "ex67",
        "depth": 21,
        "runtime": 5.322000026702881,
        "test": 93.09375,
        "train": 100.0,
        "valid": 93.5
      },
      {
        "#gates": 842,
        "benchmark": "ex73",
        "depth": 26,
        "runtime": 5.4039998054504395,
        "test": 93.46875,
        "train": 100.0,
        "valid": 93.125
      },
      {
        "#gates": 467,
        "benchmark": "ex81",
        "depth": 27,
        "runtime": 10.079999923706055,
        "test": 90.015625,
        "train": 100.0,
        "valid": 90.65625
      },
      {
        "#gates": 643,
        "benchmark": "ex80",
        "depth": 34,
        "runtime": 11.760000228881836,
        "test": 86.703125,
        "train": 100.0,
        "valid": 87.125
      },
      {
        "#gates": 277,
        "benchmark": "ex83",
        "depth": 22,
        "runtime": 7.568999767303467,
        "test": 95.546875,
        "train": 100.0,
        "valid": 95.59375
      },
      {
        "#gates": 350,
        "benchmark": "ex82",
        "depth": 31,
        "runtime": 9.086000442504883,
        "test": 93.046875,
        "train": 100.0,
        "valid": 93.046875
      },
      {
        "#gates": 1531,
        "benchmark": "ex75",
        "depth": 25,
        "runtime": 7.421000003814697,
        "test": 80.109375,
        "train": 100.0,
        "valid": 81.046875
      },
      {
        "#gates": 1583,
        "benchmark": "ex76",
        "depth": 24,
        "runtime": 6.864999771118164,
        "test": 80.53125,
        "train": 100.0,
        "valid": 80.9375
      },
      {
        "#gates": 350,
        "benchmark": "ex84",
        "depth": 31,
        "runtime": 9.762999534606934,
        "test": 94.484375,
        "train": 100.0,
        "valid": 94.078125
      },
      {
        "#gates": 1592,
        "benchmark": "ex79",
        "depth": 24,
        "runtime": 6.675000190734863,
        "test": 80.6875,
        "train": 100.0,
        "valid": 81.015625
      },
      {
        "#gates": 1592,
        "benchmark": "ex77",
        "depth": 24,
        "runtime": 7.013000011444092,
        "test": 80.6875,
        "train": 100.0,
        "valid": 81.015625
      },
      {
        "#gates": 314,
        "benchmark": "ex86",
        "depth": 27,
        "runtime": 7.729000091552734,
        "test": 94.796875,
        "train": 100.0,
        "valid": 95.140625
      },
      {
        "#gates": 338,
        "benchmark": "ex85",
        "depth": 30,
        "runtime": 9.824000358581543,
        "test": 95.125,
        "train": 100.0,
        "valid": 94.734375
      },
      {
        "#gates": 335,
        "benchmark": "ex87",
        "depth": 26,
        "runtime": 9.373000144958496,
        "test": 94.78125,
        "train": 100.0,
        "valid": 94.75
      },
      {
        "#gates": 388,
        "benchmark": "ex88",
        "depth": 25,
        "runtime": 9.196999549865723,
        "test": 93.71875,
        "train": 100.0,
        "valid": 94.328125
      },
      {
        "#gates": 362,
        "benchmark": "ex89",
        "depth": 25,
        "runtime": 9.14799976348877,
        "test": 94.421875,
        "train": 100.0,
        "valid": 94.53125
      },
      {
        "#gates": 3376,
        "benchmark": "ex78",
        "depth": 29,
        "runtime": 12.713000297546387,
        "test": 56.78125,
        "train": 100.0,
        "valid": 57.078125
      },
      {
        "#gates": 835,
        "benchmark": "ex95",
        "depth": 52,
        "runtime": 64.61799621582031,
        "test": 73.3125,
        "train": 100.0,
        "valid": 73.8125
      },
      {
        "#gates": 994,
        "benchmark": "ex93",
        "depth": 53,
        "runtime": 68.80400085449219,
        "test": 68.796875,
        "train": 99.921875,
        "valid": 69.34375
      },
      {
        "#gates": 1175,
        "benchmark": "ex92",
        "depth": 95,
        "runtime": 80.1449966430664,
        "test": 61.859375,
        "train": 99.90625,
        "valid": 63.09375
      },
      {
        "#gates": 1235,
        "benchmark": "ex91",
        "depth": 61,
        "runtime": 92.7750015258789,
        "test": 59.34375,
        "train": 100.0,
        "valid": 59.515625
      },
      {
        "#gates": 1335,
        "benchmark": "ex90",
        "depth": 64,
        "runtime": 93.00299835205078,
        "test": 53.9375,
        "train": 99.96875,
        "valid": 55.25
      },
      {
        "#gates": 1273,
        "benchmark": "ex94",
        "depth": 73,
        "runtime": 87.86199951171875,
        "test": 57.5,
        "train": 99.921875,
        "valid": 56.453125
      },
      {
        "#gates": 1175,
        "benchmark": "ex96",
        "depth": 61,
        "runtime": 82.25599670410156,
        "test": 62.46875,
        "train": 99.96875,
        "valid": 63.578125
      },
      {
        "#gates": 1226,
        "benchmark": "ex97",
        "depth": 58,
        "runtime": 85.03199768066406,
        "test": 62.140625,
        "train": 99.953125,
        "valid": 62.1875
      },
      {
        "#gates": 1158,
        "benchmark": "ex98",
        "depth": 53,
        "runtime": 48.94499969482422,
        "test": 61.203125,
        "train": 100.0,
        "valid": 62.9375
      },
      {
        "#gates": 1131,
        "benchmark": "ex99",
        "depth": 44,
        "runtime": 50.20899963378906,
        "test": 63.75,
        "train": 100.0,
        "valid": 63.9375
      }
    ],
    "version": "d9d3b71"
  }
]
