[
  {
    "entries": [
      {
        "RT 4": 0.002947411,
        "benchmark": "c17",
        "cec 4": true,
        "depth": 3,
        "depth 4": 3,
        "size": 6,
        "size 4": 6
      },
      {
        "RT 4": 0.154633674,
        "benchmark": "c432",
        "cec 4": true,
        "depth": 26,
        "depth 4": 20,
        "size": 208,
        "size 4": 232
      },
      {
        "RT 4": 0.450218859,
        "benchmark": "c499",
        "cec 4": true,
        "depth": 19,
        "depth 4": 16,
        "size": 398,
        "size 4": 473
      },
      {
        "RT 4": 0.629780991,
        "benchmark": "c880",
        "cec 4": true,
        "depth": 25,
        "depth 4": 16,
        "size": 325,
        "size 4": 360
      },
      {
        "RT 4": 0.492130586,
        "benchmark": "c1355",
        "cec 4": true,
        "depth": 25,
        "depth 4": 16,
        "size": 502,
        "size 4": 473
      },
      {
        "RT 4": 0.900076838,
        "benchmark": "c1908",
        "cec 4": true,
        "depth": 27,
        "depth 4": 20,
        "size": 341,
        "size 4": 429
      },
      {
        "RT 4": 1.010064276,
        "benchmark": "c2670",
        "cec 4": true,
        "depth": 20,
        "depth 4": 15,
        "size": 716,
        "size 4": 726
      },
      {
        "RT 4": 1.932503338,
        "benchmark": "c3540",
        "cec 4": true,
        "depth": 41,
        "depth 4": 28,
        "size": 1024,
        "size 4": 1101
      },
      {
        "RT 4": 3.460098228,
        "benchmark": "c5315",
        "cec 4": true,
        "depth": 37,
        "depth 4": 24,
        "size": 1776,
        "size 4": 1997
      },
      {
        "RT 4": 1.711681563,
        "benchmark": "c6288",
        "cec 4": true,
        "depth": 120,
        "depth 4": 65,
        "size": 2337,
        "size 4": 3320
      },
      {
        "RT 4": 3.701291469,
        "benchmark": "c7552",
        "cec 4": true,
        "depth": 26,
        "depth 4": 18,
        "size": 1469,
        "size 4": 1606
      }
    ],
    "version": "b8a9df40"
  }
]
